mapconfig/__init__.py
mapconfig/map.py
mapconfig/weather.py
mapconfig-1.0.2.dist-info/licenses/LICENCE
mapconfig-1.0.2.dist-info/METADATA
mapconfig-1.0.2.dist-info/WHEEL
mapconfig-1.0.2.dist-info/top_level.txt
mapconfig-1.0.2.dist-info/RECORD
