Metadata-Version: 2.4
Name: mapconfig
Version: 1.0.2
Summary: A simple Python library for creating interactive maps with markers, circles, and custom icons
Author: cyrus-spc-tech
Author-email: tanishgupta12389@gmail.com
Classifier: License :: OSI Approved :: MIT License
Classifier: Programming Language :: Python :: 3
Classifier: Programming Language :: Python :: 3.12
Requires-Python: >=3.6
License-File: LICENCE
Requires-Dist: folium>=0.19.0
Requires-Dist: requests>=2.25.0
Dynamic: author
Dynamic: author-email
Dynamic: classifier
Dynamic: description
Dynamic: description-content-type
Dynamic: license-file
Dynamic: requires-dist
Dynamic: requires-python
Dynamic: summary
